pypi/__init__.py
pypi/thesum.py
Arithemetic-0.1.dist-info/METADATA
Arithemetic-0.1.dist-info/WHEEL
Arithemetic-0.1.dist-info/top_level.txt
Arithemetic-0.1.dist-info/RECORD
