Metadata-Version: 2.1
Name: Arithemetic
Version: 0.1
Summary: This is sample package
Author: madhuri
Author-email: madhurichowhan.official@gmail.com
Keywords: arithmetic,math,mathematics
Classifier: Development Status :: 1 - Planning
Classifier: Intended Audience :: Developers
Classifier: Programming Language :: Python :: 3
Classifier: Operating System :: Unix
Classifier: Operating System :: MacOS :: MacOS X
Classifier: Operating System :: Microsoft :: Windows
